Metadata-Version: 1.0
Name: cambot
Version: 1.1.0
Summary: CamBot - Slack UniFi Video Camera Bot.
Home-page: https://github.com/ampledata/cambot
Author: Greg Albrecht
Author-email: oss@undef.net
License: Copyright 2017 Greg Albrecht
